laGPy/__init__.py
laGPy/_version.py
laGPy/covar.py
laGPy/gamma.py
laGPy/gp.py
laGPy/laGPy.py
laGPy/matrix.py
laGPy/order.py
laGPy/params.py
laGPy/versioneer.py
laGPy/utils/__init__.py
laGPy/utils/brent_fmin.py
laGPy/utils/distance.py
lagpy-2.2.1.dist-info/licenses/LICENSE
lagpy-2.2.1.dist-info/METADATA
lagpy-2.2.1.dist-info/WHEEL
lagpy-2.2.1.dist-info/top_level.txt
lagpy-2.2.1.dist-info/RECORD
